midfield/__init__.py
midfield/validators.py
midfield-0.1.0.dist-info/LICENSE
midfield-0.1.0.dist-info/METADATA
midfield-0.1.0.dist-info/WHEEL
midfield-0.1.0.dist-info/top_level.txt
midfield-0.1.0.dist-info/RECORD
