Metadata-Version: 2.1
Name: midfield
Version: 0.1.0
Summary: A package to validate prompts using an external API.
Home-page: https://midfield.ai
Author: Midfield Team
Author-email: admin@midfield.ai
License: MIT
Classifier: Development Status :: 3 - Alpha
Classifier: Intended Audience :: Developers
Classifier: License :: OSI Approved :: MIT License
Classifier: Programming Language :: Python :: 3
Classifier: Programming Language :: Python :: 3.6
Classifier: Programming Language :: Python :: 3.7
Classifier: Programming Language :: Python :: 3.8
Classifier: Programming Language :: Python :: 3.9
License-File: LICENSE
Requires-Dist: requests
